taelcore/__init__.py
taelcore/taelcore.py
test/__init__.py
taelcore-1.3.1.dist-info/METADATA
taelcore-1.3.1.dist-info/WHEEL
taelcore-1.3.1.dist-info/top_level.txt
taelcore-1.3.1.dist-info/RECORD
